LICENSE.txt
README.md
setup.py
xuance/__init__.py
xuance.egg-info/PKG-INFO
xuance.egg-info/SOURCES.txt
xuance.egg-info/dependency_links.txt
xuance.egg-info/requires.txt
xuance.egg-info/top_level.txt
xuance/common/__init__.py
xuance/common/callback.py
xuance/common/common_tools.py
xuance/common/memory_offline.py
xuance/common/memory_tools.py
xuance/common/memory_tools_marl.py
xuance/common/offline_util.py
xuance/common/segtree_tool.py
xuance/common/statistic_tools.py
xuance/common/tuning_tools/__init__.py
xuance/common/tuning_tools/tuning_tool.py
xuance/common/tuning_tools/hyperparameters/__init__.py
xuance/common/tuning_tools/hyperparameters/a2c.py
xuance/common/tuning_tools/hyperparameters/c51.py
xuance/common/tuning_tools/hyperparameters/coma.py
xuance/common/tuning_tools/hyperparameters/dcg.py
xuance/common/tuning_tools/hyperparameters/ddpg.py
xuance/common/tuning_tools/hyperparameters/ddqn.py
xuance/common/tuning_tools/hyperparameters/dqn.py
xuance/common/tuning_tools/hyperparameters/drqn.py
xuance/common/tuning_tools/hyperparameters/dueldqn.py
xuance/common/tuning_tools/hyperparameters/iac.py
xuance/common/tuning_tools/hyperparameters/iddpg.py
xuance/common/tuning_tools/hyperparameters/ippo.py
xuance/common/tuning_tools/hyperparameters/iql.py
xuance/common/tuning_tools/hyperparameters/isac.py
xuance/common/tuning_tools/hyperparameters/maddpg.py
xuance/common/tuning_tools/hyperparameters/mappo.py
xuance/common/tuning_tools/hyperparameters/masac.py
xuance/common/tuning_tools/hyperparameters/matd3.py
xuance/common/tuning_tools/hyperparameters/noisydqn.py
xuance/common/tuning_tools/hyperparameters/perdqn.py
xuance/common/tuning_tools/hyperparameters/pg.py
xuance/common/tuning_tools/hyperparameters/ppg.py
xuance/common/tuning_tools/hyperparameters/ppo.py
xuance/common/tuning_tools/hyperparameters/qmix.py
xuance/common/tuning_tools/hyperparameters/qrdqn.py
xuance/common/tuning_tools/hyperparameters/qtran.py
xuance/common/tuning_tools/hyperparameters/sac.py
xuance/common/tuning_tools/hyperparameters/td3.py
xuance/common/tuning_tools/hyperparameters/vdac.py
xuance/common/tuning_tools/hyperparameters/vdn.py
